test/__init__.py
test/test_topsis.py
topsis-102103355/__init__.py
topsis-102103355/topsis.py
Topsis_RishavJ_102103355-0.1.0.dist-info/LICENSE
Topsis_RishavJ_102103355-0.1.0.dist-info/METADATA
Topsis_RishavJ_102103355-0.1.0.dist-info/WHEEL
Topsis_RishavJ_102103355-0.1.0.dist-info/entry_points.txt
Topsis_RishavJ_102103355-0.1.0.dist-info/top_level.txt
Topsis_RishavJ_102103355-0.1.0.dist-info/RECORD
